longqinsi_reader/__init__.py
longqinsi_reader/__main__.py
longqinsi_reader/multireader.py
longqinsi_reader/util/__init__.py
longqinsi_reader/util/writer.py
longqinsi_reader-1.0.0.dist-info/METADATA
longqinsi_reader-1.0.0.dist-info/WHEEL
longqinsi_reader-1.0.0.dist-info/top_level.txt
longqinsi_reader-1.0.0.dist-info/RECORD
